{
  "objective": "把 S26 已練熟嘅『判方向』能力升級到時間壓力下:喺聊天室計時(timed)親手做 12 題微積分混合題(calculus mixed problems),開計時器一氣呵成做完、記低總用時同第一次命中數(first-pass accuracy),做完逐題訂正並把錯題分為『判方向錯/計錯/趕時間睇漏』三類。重點唔係學新公式,而係把微積分由『識做』逼到『又快又準』:壓死趕時間時最易犯嘅三個失分位——未判方向就落筆、eᵏˣ 個 k 乘定除放反、漏寫 +C;練到計時命中 ≥ 10/12 且用時有改善,為 S28 現場溫度/bond profile 曲線嘅快速讀題收官打底",
  "fieldLink": "",
  "checkpoints": [
    { "id": "c1", "text": "有真係開計時器,由第 1 題做到第 12 題一氣呵成、中途冇對答案/翻書,當考試咁做完" },
    { "id": "c2", "text": "記低咗總用時同第一次命中數(12 題第一次就啱幾多題),呢兩個數先係本節成績" },
    { "id": "c3", "text": "即使趕時間,每題都有先寫方向(微分/積分)後落筆,冇因為趕就跳判方向呢一步" },
    { "id": "c4", "text": "處理 eᵏˣ 時係數對應啱:求導乘 k(d/dx e³ˣ=3e³ˣ)、積分除 k(∫e²ˣdx=½e²ˣ),趕時間都冇放反" },
    { "id": "c5", "text": "判得清定積分(有上下限、唔寫 +C)同不定積分(求返原函數、要寫 +C),趕時間都冇漏 +C" },
    { "id": "c6", "text": "做完把每條錯題分咗『判方向錯/計錯/趕時間睇漏』三類,圈起、訂正並揀同型號題重做到命中 ≥ 10/12" }
  ],
  "resources": [
    { "type": "link", "label": "(選看)Paul's Online Math Notes:Calculus I 全章(微分與積分混合練習,可自設計時)", "url": "https://tutorial.math.lamar.edu/Classes/CalcI/CalcI.aspx" }
  ],
  "charts": [],
  "quiz": [],
  "chatPracticeHints": [
    "計時:一氣呵成做完先對答案",
    "趕都要先判方向後落筆",
    "錯題分判錯/計錯/睇漏三類"
  ]
}
