{
  "objective": "由第一定律（S51，能量守恆）進一步引入『方向』概念：用熵 S 量度一個巨觀狀態對應幾多種微觀排法（亂度），掌握主公式玻茲曼熵 S＝k_B·lnΩ（Ω＝微觀狀態數、Ω 大則熵大；套 ln 令兩系統合埋時熵可相加）；理解第二定律 ΔS_孤立 ≥ 0（孤立系統熵只升不自減，=0 可逆、>0 真實不可逆過程）；識用可逆傳熱熵變 ΔS＝Q_rev/T（T 必用 K、吸熱+放熱−）算傳熱總熵變並證明熱由高溫往低溫流會令總熵升；識用 ΔS_總＝ΔS_系統+ΔS_環境 判自發（總熵>0 即自發），並明白單一系統熵可跌、但系統+環境總帳必升（如水結冰、雪櫃、擴散）。核心直覺：自然界唔係向能量最低、而係向總熵最高走——呢個正係 S54 可逆吸放熱、S60 擴散（往亂度高走）同將來固態熱力學 ΔG＝ΔH−TΔS 嘅方向因子地基",
  "fieldLink": "封裝現場好多『自己會發生、倒返轉唔會』嘅現象本質都係熵增驅動：①擴散會自發——兩種原子／摻雜物放埋一齊會自己滲入變均勻、唔會自己分開，因為『混合均勻』對應嘅微觀排法 Ω 遠多過『各自分開』，呢個正係焊料／金屬界面互擴散（intermetallic 生成）同 S60 擴散嘅底層驅動力；②熱由熱端往冷端流——Pedestal、Bond Head 溫度唔均勻時熱一定自己往凍走（ΔS=Q/T 已證總熵升），唔會倒轉；③急冷／退火唔會自己逆轉——係動力學凍結咗熵增，但畀夠溫度時間始終向總熵最高／自由能最低行。一句記住：自然界向『總熵最高』而唔係『能量最低』走",
  "checkpoints": [
    { "id": "c1", "text": "講得出熵（entropy）量度『一個睇得到嘅巨觀狀態對應幾多種睇唔到嘅微觀排法（亂度）』，排法越多熵越高，唔會把熵當成能量（單位 J/K 而非 J）" },
    { "id": "c2", "text": "識用主公式 S＝k_B·lnΩ：Ω（微觀狀態數）越大則 S 越大，並講得出點解套 ln（Ω 相乘 → ln 變相加，令兩系統合埋時熵可加），同 Ω=1 時 S=0" },
    { "id": "c3", "text": "講得出第二定律 ΔS_孤立 ≥ 0（孤立系統熵只會升或不變、唔會自己減少），=0 對應可逆、>0 對應真實不可逆過程" },
    { "id": "c4", "text": "識用 ΔS＝Q_rev/T 算可逆傳熱熵變：T 一定用 K（唔可 °C）、吸熱 Q 帶+、放熱帶−，並能算出熱由高溫往低溫流時 ΔS_總>0（如 400K 放 1000J 畀 300K，總熵 +0.83 J/K）" },
    { "id": "c5", "text": "識用 ΔS_總＝ΔS_系統+ΔS_環境 判自發（總熵>0 即自發），並明白單一系統熵可以跌（如水結冰、雪櫃整凍嘢）但系統+環境總帳仍升，唔會誤以為違反第二定律" },
    { "id": "c6", "text": "講得出擴散／混合／傳熱自發嘅本質係『往微觀排法多（高熵）方向走』，並能用『自然界向總熵最高而非能量最低走』解釋現場擴散現象" }
  ],
  "resources": [
    { "type": "video", "label": "（選看）Khan Academy：Entropy intuition / Second law of thermodynamics（熵與第二定律直覺）", "url": "https://www.khanacademy.org" }
  ],
  "charts": [],
  "quiz": [
    {
      "type": "single",
      "difficulty": "basic",
      "q": "熵（entropy）大致量度緊咩？",
      "options": [
        "系統嘅亂度，即一個巨觀狀態對應幾多種微觀排法",
        "系統嘅總能量",
        "系統嘅溫度",
        "系統嘅體積"
      ],
      "answer": 0,
      "explain": "熵（entropy）量度嘅係『一個睇得到嘅巨觀狀態（macrostate）底下，對應幾多種睇唔到嘅微觀排法（microstate）』——即亂度。微觀排法（Ω）越多 → 熵越高 → 越大機會自然出現。常見錯選『總能量』：能量係第一定律嘅嘢、講總數平唔平（單位 J）；熵係第二定律嘅嘢、講方向／亂度（單位 J/K），兩者唔同。"
    },
    {
      "type": "truefalse",
      "difficulty": "basic",
      "q": "第二定律話：一個孤立系統（唔同外界交換熱或物質）入面，總熵只會增加或不變，唔會自己減少。",
      "answer": true,
      "explain": "啱。第二定律：ΔS_孤立 ≥ 0。=0 對應理想化嘅可逆過程（無限慢、無耗散）；>0 對應所有真實過程（傳熱、混合、擴散等不可逆過程）。所以孤立系統永遠向『總熵最高』方向行，唔會自己倒返低熵——呢個正係『熱會自己由熱流向凍、墨汁會自己散開』嘅根本原因。"
    },
    {
      "type": "single",
      "difficulty": "standard",
      "q": "玻茲曼公式 S＝k_B·lnΩ 入面，微觀狀態數 Ω 越大，熵 S 會點？同埋點解定義要套 ln（自然對數）？",
      "options": [
        "Ω 越大 S 越大；套 ln 係為咗令兩系統合埋時熵可相加（Ω 相乘 → lnΩ 變相加）",
        "Ω 越大 S 越細；套 ln 純粹數學習慣",
        "Ω 越大 S 不變；ln 令數值好睇啲",
        "Ω 越大 S 越大；ln 因為 Ω 一定係負數"
      ],
      "answer": 0,
      "explain": "ln 係遞增函數，所以 Ω（微觀排法數）越大、lnΩ 越大、熵 S 越大——把『亂法有幾多種』量化咗。套 ln 嘅原因：兩個獨立系統合埋，微觀排法係相乘 Ω_總＝Ω₁×Ω₂；套 ln 後 ln(Ω₁Ω₂)＝lnΩ₁+lnΩ₂，所以 S_總＝S₁+S₂，令熵變成可相加（廣延性質）。另外 Ω=1（完美有序）時 ln1＝0，故 S＝0。錯選把 ln 當成純習慣或為好睇，漏咗『令熵可加』先係真正原因。"
    },
    {
      "type": "single",
      "difficulty": "standard",
      "q": "水結冰時，系統（水→冰）排得整齊、Ω 變細，所以系統熵跌咗（ΔS_系統<0）。咁點解冬天水仲會自己結冰？",
      "options": [
        "結冰放出嘅凝固熱被周圍冷環境吸收、環境熵升得更多，總熵 ΔS_總＝ΔS_系統+ΔS_環境 仍然>0",
        "因為第二定律喺低溫之下唔再成立",
        "因為冰嘅能量較低，自然界一定向能量最低走",
        "其實水結冰唔係自發過程"
      ],
      "answer": 0,
      "explain": "第二定律管嘅係『系統＋環境』嘅總熵，唔係系統自己。水結冰時系統熵跌（ΔS_系統<0），但放出嘅凝固熱被夠凍嘅環境吸收，由 ΔS=Q/T，環境溫度較低（分母細）故環境賺嘅熵 |Q/T_環境| 大過系統蝕嘅 |Q/T_系統|，所以 ΔS_總>0、自發。錯選『低溫唔成立』錯（定律永遠成立）；『向能量最低走』唔準確（自然界向總熵最高走，要計溫度時由 ΔG＝ΔH−TΔS 權衡）；雪櫃整凍嘢、生物長有序結構同理，都係靠把更多熵掉去環境換返嚟。"
    }
  ],
  "chatPracticeHints": [
    "ΔS=Q/T 嘅 T 要用 K",
    "系統熵可跌但總熵照升",
    "熵≠能量，自發睇總熵"
  ]
}
